topsis_package_102013372/__init__.py
topsis_package_102013372/topsis.py
topsis_tanisha_102103372-0.1.dist-info/License.txt
topsis_tanisha_102103372-0.1.dist-info/METADATA
topsis_tanisha_102103372-0.1.dist-info/WHEEL
topsis_tanisha_102103372-0.1.dist-info/top_level.txt
topsis_tanisha_102103372-0.1.dist-info/RECORD
