Metadata-Version: 2.1
Name: topsis-tanisha-102103372
Version: 0.1
Summary: Topsis Implementation
Author: Tanisha Sood
Author-email: tanisha.sood24@gmail.com
Classifier: Programming Language :: Python :: 3
Classifier: License :: OSI Approved :: MIT License
Classifier: Operating System :: OS Independent
License-File: License.txt
